{
  "id": "10-05",
  "month": 10,
  "day": 5,
  "dateLabel": "5 de Outubro",
  "dayContext": "História recuperada do arquivo original.",
  "title": "O Sultão Bonacheirão",
  "author": "António Torrado",
  "illustrator": "Cristina Malaquias",
  "textSegments": [
    {
      "layer": "archive-placeholder",
      "paragraphs": [
        "Texto original ainda não extraído. Consulta o PDF ou a página arquivada nas ligações de recuperação."
      ]
    }
  ],
  "glossary": [
    {
      "id": "8",
      "term": "bonacheirão",
      "definition": "Bondoso / simples / ingénuo."
    },
    {
      "id": "9",
      "term": "iminência",
      "definition": "Que pode acontecer a qualquer momento / proximidade."
    },
    {
      "id": "10",
      "term": "cortesãos",
      "definition": "Homens da corte."
    },
    {
      "id": "11",
      "term": "enfarruscou",
      "definition": "Sujou de foligem ou carvão."
    }
  ],
  "assets": {
    "background": "/recovered/0000/10/05/images/lrg7s5witttge5zihlxqav7uajhl3exz/Imagens/Background.jpg",
    "icon": "/recovered/0000/10/05/images/gosu2cd6rustz3465dtnjrrtpjshpb5a/Imagens/icone.jpg",
    "printPdf": null,
    "originalAudioSwf": "/recovered/0000/10/05/audio/2x4q3bmn6igf3eq5ditg3r5bfvbdtpjb/um.swf",
    "recoveredAudio": null,
    "gallery": []
  },
  "recovery": {
    "text": "pending-extraction",
    "illustration": "archive-originals",
    "originalAudio": "archive-swf-reference",
    "recoveredAudio": "missing",
    "pdf": "missing",
    "completeness": "needs-text-extraction"
  },
  "provenance": {
    "storyPage": "/recovered/0000/10/05/html/w7okp724wny4gocnp2qc42scjzmhx63s/historia.aspx",
    "printPdf": null,
    "archiveDay": "/recovered/0000/10/05/",
    "notes": "Dia presente no calendário, mas sem texto HTML extraível no índice recuperado. PDF/assets ficam ligados quando existem."
  },
  "editorialNotes": [
    "A página preserva o texto HTML original quando disponível; a revisão editorial fina continua pendente para muitos dias.",
    "As ilustrações apresentadas são os ficheiros originais recuperados, normalizados para navegação no site moderno."
  ]
}
